AUTHORS
LICENSE
MANIFEST.in
README.rst
setup.py
./PyTangoArchiving/scripts/PyExtractor
./PyTangoArchiving/scripts/archiving2csv
./PyTangoArchiving/scripts/archiving2plot
./PyTangoArchiving/scripts/archiving_service
./PyTangoArchiving/scripts/ctarchiving
./PyTangoArchiving/scripts/taurusfinder
PyTangoArchiving/VERSION
PyTangoArchiving/__init__.py
PyTangoArchiving/archiving.py
PyTangoArchiving/check.py
PyTangoArchiving/common.py
PyTangoArchiving/dbs.py
PyTangoArchiving/files.py
PyTangoArchiving/reader.py
PyTangoArchiving/schemas.py
PyTangoArchiving/utils.py
PyTangoArchiving/web.py
PyTangoArchiving.egg-info/PKG-INFO
PyTangoArchiving.egg-info/SOURCES.txt
PyTangoArchiving.egg-info/dependency_links.txt
PyTangoArchiving.egg-info/entry_points.txt
PyTangoArchiving.egg-info/not-zip-safe
PyTangoArchiving.egg-info/requires.txt
PyTangoArchiving.egg-info/top_level.txt
PyTangoArchiving/hdbpp/__init__.py
PyTangoArchiving/hdbpp/alter_datetime.sql
PyTangoArchiving/hdbpp/api.py
PyTangoArchiving/hdbpp/check_and_recover_attributes.py
PyTangoArchiving/hdbpp/config.py
PyTangoArchiving/hdbpp/create_hdb++_mysql.sql
PyTangoArchiving/hdbpp/create_hdbpp_devices.py
PyTangoArchiving/hdbpp/decimate.py
PyTangoArchiving/hdbpp/maintenance.py
PyTangoArchiving/hdbpp/multi.py
PyTangoArchiving/hdbpp/periodic.py
PyTangoArchiving/hdbpp/privileges.sh
PyTangoArchiving/hdbpp/privileges.sql
PyTangoArchiving/hdbpp/query.py
PyTangoArchiving/hdbpp/subscribe_attributes.py
PyTangoArchiving/scripts/THIS_FOLDER_SHOULD_NOT_HAVE__init.py
PyTangoArchiving/scripts/__init__.py
PyTangoArchiving/scripts/alter_snap_db.py
PyTangoArchiving/scripts/archiver_health_check.py
PyTangoArchiving/scripts/archiving_load.py
PyTangoArchiving/scripts/archiving_report.py
PyTangoArchiving/scripts/archiving_transfer.py
PyTangoArchiving/scripts/check_db_growth.py
PyTangoArchiving/scripts/check_partitions.py
PyTangoArchiving/scripts/db_repair.py
PyTangoArchiving/scripts/decimate_table.py
PyTangoArchiving/scripts/inspect_hdbpp_hosts.py
PyTangoArchiving/scripts/start_hdbpp_archivers.py
PyTangoArchiving/servers/__init__.py
PyTangoArchiving/servers/PyExtractor/PyExtractor.py
PyTangoArchiving/servers/PyExtractor/__init__.py
PyTangoArchiving/servers/SchemaManager/SchemaManager.py
